{
	"class" : {
		"borderWidth" : "tfel 4/28/2011 23:02:53.335",
		"interestingSystemEvents" : "sp 6/28/2012 09:35:27.491",
		"on:in:forCategory:" : "ag 12/9/2011 14:43:01.271",
		"systemEventHandler" : "tfel 5/1/2011 00:45:29.442" },
	"instance" : {
		"accept:" : "tfel 6/28/2012 07:02:32.324",
		"addMethod" : "sp 7/5/2012 13:39:57.906",
		"allEntries" : "ag 12/9/2011 14:01:49.284",
		"allEntriesCount" : "ag 7/2/2012 14:13:09.867",
		"buildMenu:" : "sp 6/4/2012 13:27:41.69",
		"category" : "tfel 7/14/2011 13:42:26.526",
		"category:" : "tfel 4/29/2011 14:30:25.182",
		"createEntries" : "ag 12/9/2011 14:46:10.803",
		"isEquivalentTo:" : "pt 6/27/2012 09:06:26.462",
		"labelEmphasis" : "ag 12/10/2011 16:30:14.502",
		"labelString" : "ag 4/18/2012 16:54:51.12",
		"methodMorphFor:" : "ag 3/8/2012 13:18:30.251",
		"methodOrCategoryEvent:" : "mp 7/16/2013 13:51:04.788",
		"mouseActions" : "ag 6/18/2012 11:16:36.849",
		"processReengineeringInto:" : "mp 7/16/2013 13:45:06.511",
		"pullUpMethodCategory" : "ag 6/13/2012 16:04:28.569",
		"pushDownMethodCategory" : "ag 7/2/2012 13:42:12.953",
		"renameCategory" : "sp 6/28/2012 09:37:05.108",
		"selectorsInCategory" : "ag 6/13/2012 16:06:38.413",
		"wantsReengineeringInto:" : "ag 6/13/2012 16:14:12.234" } }
